bonxai/__init__.py
bonxai/_version.py
bonxai/example.py
bonxai/widget.py
bonxai/labextension/package.json
bonxai/labextension/static/108.23ad6e269281ac8fcc48.js
bonxai/labextension/static/132.94d3969a67cfb47cbbdb.js
bonxai/labextension/static/285.8217fca0e09a88793c35.js
bonxai/labextension/static/344.812f20d8164116c2af7c.js
bonxai/labextension/static/384.1f5603aca89b72e166df.js
bonxai/labextension/static/493.34aef21d5d25d4977fa3.js
bonxai/labextension/static/600.15ca81d21dc08dd850d4.js
bonxai/labextension/static/600.15ca81d21dc08dd850d4.js.LICENSE.txt
bonxai/labextension/static/693.a16a48e43b121674a96e.js
bonxai/labextension/static/727.7c9b1efcbca8326e44e9.js
bonxai/labextension/static/868.8c5d3421dde8e45893be.js
bonxai/labextension/static/871.0685090689ea8f246831.js
bonxai/labextension/static/871.0685090689ea8f246831.js.LICENSE.txt
bonxai/labextension/static/remoteEntry.108a08d7b93ba8b363af.js
bonxai/labextension/static/style.js
bonxai/labextension/static/third-party-licenses.json
bonxai/nbextension/extension.js
bonxai/nbextension/index.js
bonxai/nbextension/index.js.LICENSE.txt
bonxai-0.1.1.data/data/etc/jupyter/nbconfig/notebook.d/bonxai.json
bonxai-0.1.1.data/data/share/jupyter/labextensions/bonxai/install.json
bonxai-0.1.1.data/data/share/jupyter/labextensions/bonxai/package.json
bonxai-0.1.1.data/data/share/jupyter/labextensions/bonxai/static/108.23ad6e269281ac8fcc48.js
bonxai-0.1.1.data/data/share/jupyter/labextensions/bonxai/static/132.94d3969a67cfb47cbbdb.js
bonxai-0.1.1.data/data/share/jupyter/labextensions/bonxai/static/285.8217fca0e09a88793c35.js
bonxai-0.1.1.data/data/share/jupyter/labextensions/bonxai/static/344.812f20d8164116c2af7c.js
bonxai-0.1.1.data/data/share/jupyter/labextensions/bonxai/static/384.1f5603aca89b72e166df.js
bonxai-0.1.1.data/data/share/jupyter/labextensions/bonxai/static/493.34aef21d5d25d4977fa3.js
bonxai-0.1.1.data/data/share/jupyter/labextensions/bonxai/static/600.15ca81d21dc08dd850d4.js
bonxai-0.1.1.dist-info/METADATA
bonxai-0.1.1.dist-info/WHEEL
bonxai-0.1.1.dist-info/top_level.txt
bonxai-0.1.1.dist-info/RECORD
